deertick/README.md
deertick/agent.py
deertick/bot.py
deertick/deertick.py
deertick/model_data.py
deertick/soap_yote.py
deertick/songwriter.py
deertick/terminal_chat.py
deertick-0.0.9.dist-info/METADATA
deertick-0.0.9.dist-info/WHEEL
deertick-0.0.9.dist-info/license
deertick-0.0.9.dist-info/top_level.txt
deertick-0.0.9.dist-info/RECORD
