Metadata-Version: 2.1
Name: deertick
Version: 0.0.9
Summary: DeerTick: A Multi-Provider Language Model Interface for interacting with various AI models across different providers, supporting both interactive chat and file-based input/output.
Author-email: Doe Sparkle <thesparkledoe@gmail.com>
Project-URL: Homepage, https://github.com/deeterbleater/deertick
Project-URL: Issues, https://github.com/deeterbleater/deertick/issues
Classifier: Programming Language :: Python :: 3
Classifier: License :: OSI Approved :: MIT License
Classifier: Operating System :: OS Independent
Requires-Python: >=3.9
License-File: license
